<collision_model>
    <object label="eggs" mesh_resource="package://demonstration_visualizer/meshes/eggs/eggs.dae" />

    <sphere id="1" x="0" y="-0.04" z="-0.01" radius="0.02" />
    <sphere id="2" x="0.04" y="-0.04" z="-0.01" radius="0.02" />
    <sphere id="3" x="0.08" y="-0.04" z="-0.01" radius="0.02" />
    <sphere id="4" x="0.12" y="-0.04" z="-0.01" radius="0.02" />
    <sphere id="5" x="-0.04" y="-0.04" z="-0.01" radius="0.02" />
    <sphere id="6" x="-0.08" y="-0.04" z="-0.01" radius="0.02" />
    <sphere id="7" x="-0.12" y="-0.04" z="-0.01" radius="0.02" />

    <sphere id="8" x="0" y="0" z="-0.01" radius="0.02" />
    <sphere id="9" x="0.04" y="0" z="-0.01" radius="0.02" />
    <sphere id="10" x="0.08" y="0" z="-0.01" radius="0.02" />
    <sphere id="11" x="0.12" y="0" z="-0.01" radius="0.02" />
    <sphere id="12" x="-0.04" y="0" z="-0.01" radius="0.02" />
    <sphere id="13" x="-0.08" y="0" z="-0.01" radius="0.02" />
    <sphere id="14" x="-0.12" y="0" z="-0.01" radius="0.02" />

    <sphere id="15" x="0" y="0.04" z="-0.01" radius="0.02" />
    <sphere id="16" x="0.04" y="0.04" z="-0.01" radius="0.02" />
    <sphere id="17" x="0.08" y="0.04" z="-0.01" radius="0.02" />
    <sphere id="18" x="0.12" y="0.04" z="-0.01" radius="0.02" />
    <sphere id="19" x="-0.04" y="0.04" z="-0.01" radius="0.02" />
    <sphere id="20" x="-0.08" y="0.04" z="-0.01" radius="0.02" />
    <sphere id="21" x="-0.12" y="0.04" z="-0.01" radius="0.02" />

    <sphere id="22" x="0" y="-0.04" z="0.02" radius="0.02" />
    <sphere id="23" x="0.04" y="-0.04" z="0.02" radius="0.02" />
    <sphere id="24" x="0.08" y="-0.04" z="0.02" radius="0.02" />
    <sphere id="25" x="0.12" y="-0.04" z="0.02" radius="0.02" />
    <sphere id="26" x="-0.04" y="-0.04" z="0.02" radius="0.02" />
    <sphere id="27" x="-0.08" y="-0.04" z="0.02" radius="0.02" />
    <sphere id="28" x="-0.12" y="-0.04" z="0.02" radius="0.02" />

    <sphere id="29" x="0" y="0" z="0.02" radius="0.02" />
    <sphere id="30" x="0.04" y="0" z="0.02" radius="0.02" />
    <sphere id="31" x="0.08" y="0" z="0.02" radius="0.02" />
    <sphere id="32" x="0.12" y="0" z="0.02" radius="0.02" />
    <sphere id="33" x="-0.04" y="0" z="0.02" radius="0.02" />
    <sphere id="34" x="-0.08" y="0" z="0.02" radius="0.02" />
    <sphere id="35" x="-0.12" y="0" z="0.02" radius="0.02" />

    <sphere id="36" x="0" y="0.04" z="0.02" radius="0.02" />
    <sphere id="37" x="0.04" y="0.04" z="0.02" radius="0.02" />
    <sphere id="38" x="0.08" y="0.04" z="0.02" radius="0.02" />
    <sphere id="39" x="0.12" y="0.04" z="0.02" radius="0.02" />
    <sphere id="40" x="-0.04" y="0.04" z="0.02" radius="0.02" />
    <sphere id="41" x="-0.08" y="0.04" z="0.02" radius="0.02" />
    <sphere id="42" x="-0.12" y="0.04" z="0.02" radius="0.02" />
</collision_model>
